datatable/__init__.py
datatable/core/BaseController.py
datatable/core/Observer.py
datatable/core/WidgetManager.py
datatable/core/__init__.py
datatable/models/__init__.py
datatable/models/datatable_model.py
datatable/models/delegates.py
datatable/themes/__init__.py
datatable/ui/__init__.py
datatable/ui/untitled.py
datatable/widgets/__init__.py
datatable/widgets/datatable.py
datatable/widgets/utils.py
datatable/widgets/handlers/DataTableHandler.py
datatable/widgets/handlers/__init__.py
pyside6_datatable_widget-1.1.0.6.dist-info/licenses/LICENSE
pyside6_datatable_widget-1.1.0.6.dist-info/METADATA
pyside6_datatable_widget-1.1.0.6.dist-info/WHEEL
pyside6_datatable_widget-1.1.0.6.dist-info/top_level.txt
pyside6_datatable_widget-1.1.0.6.dist-info/RECORD
