Metadata-Version: 2.4
Name: pyside6-datatable-widget
Version: 1.1.0.6
Summary: A PySide6 DataTable widget with jQuery DataTable-like functionality
Home-page: https://github.com/ultra-bugs/pyside6-datatable-widget
Author: Zuko
Author-email: tansautn@gmail.com
License: GPLv3
Project-URL: Bug Tracker, https://github.com/ultra-bugs/pyside6-datatable-widget/issues
Classifier: Programming Language :: Python :: 3
Classifier: License :: OSI Approved :: MIT License
Classifier: Operating System :: OS Independent
Classifier: Development Status :: 4 - Beta
Classifier: Intended Audience :: Developers
Classifier: Topic :: Software Development :: User Interfaces
Classifier: License :: OSI Approved :: GNU General Public License v3 (GPLv3)
Requires-Python: >=3.10
License-File: LICENSE
Requires-Dist: PySide6>=6.1.0
Dynamic: author
Dynamic: author-email
Dynamic: classifier
Dynamic: description
Dynamic: description-content-type
Dynamic: home-page
Dynamic: license
Dynamic: license-file
Dynamic: project-url
Dynamic: requires-dist
Dynamic: requires-python
Dynamic: summary
